CHANGELOG.rst
LICENSE
MANIFEST.in
README.rst
setup.py
base_project/__init__.py
base_project/manage.py
base_project/settings.py
base_project/urls.py
base_project/static/css/reset.css
base_project/static/css/style.css
base_project/static/css/icons/icon.css
base_project/static/img/django.png
base_project/templates/404.html
base_project/templates/500.html
base_project/templates/base.html
base_project/templates/home.html
django_mediagenerator_kensho.egg-info/PKG-INFO
django_mediagenerator_kensho.egg-info/SOURCES.txt
django_mediagenerator_kensho.egg-info/dependency_links.txt
django_mediagenerator_kensho.egg-info/requires.txt
django_mediagenerator_kensho.egg-info/top_level.txt
mediagenerator/__init__.py
mediagenerator/api.py
mediagenerator/base.py
mediagenerator/middleware.py
mediagenerator/read_write_lock.py
mediagenerator/settings.py
mediagenerator/utils.py
mediagenerator/contrib/__init__.py
mediagenerator/contrib/jinja2ext.py
mediagenerator/contrib/jinja2install.py
mediagenerator/filters/__init__.py
mediagenerator/filters/clever.py
mediagenerator/filters/closure.py
mediagenerator/filters/coffeescript.py
mediagenerator/filters/concat.py
mediagenerator/filters/cssurl.py
mediagenerator/filters/handlebars.py
mediagenerator/filters/i18n.py
mediagenerator/filters/less.py
mediagenerator/filters/libsass.py
mediagenerator/filters/media_url.py
mediagenerator/filters/pyjs_filter.py
mediagenerator/filters/pyvascript_filter.py
mediagenerator/filters/sass.py
mediagenerator/filters/sass_compass.rb
mediagenerator/filters/sass_paths.rb
mediagenerator/filters/template.py
mediagenerator/filters/uglifier.py
mediagenerator/filters/yuicompressor.py
mediagenerator/filters/pyjslibs/dynamic.py
mediagenerator/filters/pyjslibs/getopt.py
mediagenerator/generators/__init__.py
mediagenerator/generators/copyfiles.py
mediagenerator/generators/manifest.py
mediagenerator/generators/bundles/__init__.py
mediagenerator/generators/bundles/base.py
mediagenerator/generators/bundles/bundles.py
mediagenerator/generators/bundles/itercompat.py
mediagenerator/generators/bundles/settings.py
mediagenerator/generators/bundles/utils.py
mediagenerator/management/__init__.py
mediagenerator/management/commands/__init__.py
mediagenerator/management/commands/generatemedia.py
