Metadata-Version: 1.1
Name: django-mediagenerator-kensho
Version: 1.6
Summary: Kensho's fork of mediagenerator
Home-page: http://www.allbuttonspressed.com/projects/django-mediagenerator
Author: Waldemar Kornewald
Author-email: wkornewald@gmail.com
License: UNKNOWN
Platform: any
Classifier: Development Status :: 5 - Production/Stable
Classifier: Environment :: Web Environment
Classifier: Framework :: Django
Classifier: Intended Audience :: Developers
Classifier: Operating System :: OS Independent
Classifier: Programming Language :: Python
Classifier: Topic :: Software Development :: Libraries :: Application Frameworks
Classifier: Topic :: Software Development :: Libraries :: Python Modules
Classifier: License :: OSI Approved :: BSD License
